cxrandomwalk_core.cpython-39-darwin.so
cxrandomwalk/__init__.py
cxrandomwalk/cxrandomwalk.py
cxrandomwalk-0.5.9.dist-info/RECORD
cxrandomwalk-0.5.9.dist-info/LICENSE
cxrandomwalk-0.5.9.dist-info/WHEEL
cxrandomwalk-0.5.9.dist-info/top_level.txt
cxrandomwalk-0.5.9.dist-info/METADATA
