Metadata-Version: 2.1
Name: cxrandomwalk
Version: 0.5.9
Summary: Library to perform random walks on complex networks.
Home-page: https://github.com/filipinascimento/cxrandomwalk
Author: Filipi N. Silva
Author-email: filipinascimento@gmail.com
Classifier: Programming Language :: Python :: 3
Classifier: License :: OSI Approved :: MIT License
Classifier: Operating System :: MacOS :: MacOS X
Classifier: Operating System :: Microsoft :: Windows
Classifier: Operating System :: POSIX :: Linux
Classifier: Development Status :: 3 - Alpha
Classifier: Programming Language :: C
Classifier: Topic :: Scientific/Engineering :: Information Analysis
Classifier: Intended Audience :: Science/Research
Requires-Python: >=3.9
License-File: LICENSE
Requires-Dist: numpy
